aap_llamaindex/__init__.py
aap_llamaindex/chain.py
aap_llamaindex/py.typed
aap_llamaindex/retriever.py
aap_llamaindex-0.1.2.dev1.dist-info/WHEEL
aap_llamaindex-0.1.2.dev1.dist-info/METADATA
aap_llamaindex-0.1.2.dev1.dist-info/RECORD
