Metadata-Version: 2.3
Name: aap-llamaindex
Version: 0.1.2.dev1
Summary: LlamaIndex integration of agent design pattern
Keywords: agent,ai,pattern,llm,llamaindex
Author: Ly Hon Quang
Author-email: Ly Hon Quang <lyhonquang@gmail.com>
License: MIT
Classifier: Programming Language :: Python :: 3.10
Classifier: Programming Language :: Python :: 3.11
Classifier: Programming Language :: Python :: 3.12
Classifier: Programming Language :: Python :: 3.13
Classifier: Programming Language :: Python :: 3.14
Classifier: Programming Language :: Python :: 3.15
Classifier: Framework :: Pydantic :: 2
Classifier: Operating System :: OS Independent
Requires-Dist: aap-core>=0.1.0
Requires-Dist: llama-index>=0.14.8
Requires-Dist: llama-index-vector-stores-weaviate ; extra == 'weaviate'
Requires-Python: >=3.10.12
Project-URL: Repository, https://github.com/quanghona/agent_design_pattern.git
Provides-Extra: weaviate
